mt3_infer/__init__.py
mt3_infer/api.py
mt3_infer/base.py
mt3_infer/cli.py
mt3_infer/exceptions.py
mt3_infer/adapters/__init__.py
mt3_infer/adapters/mr_mt3.py
mt3_infer/adapters/mt3_pytorch.py
mt3_infer/adapters/vocab_utils.py
mt3_infer/adapters/yourmt3.py
mt3_infer/config/checkpoints.yaml
mt3_infer/config/external_integrations.yaml
mt3_infer/models/__init__.py
mt3_infer/models/mr_mt3/__init__.py
mt3_infer/models/mr_mt3/t5.py
mt3_infer/models/mt3_pytorch/__init__.py
mt3_infer/models/mt3_pytorch/t5.py
mt3_infer/models/mt3_pytorch/contrib/__init__.py
mt3_infer/models/mt3_pytorch/contrib/event_codec.py
mt3_infer/models/mt3_pytorch/contrib/metrics_utils.py
mt3_infer/models/mt3_pytorch/contrib/note_sequences.py
mt3_infer/models/mt3_pytorch/contrib/preprocessor.py
mt3_infer/models/mt3_pytorch/contrib/run_length_encoding.py
mt3_infer/models/mt3_pytorch/contrib/spectrograms.py
mt3_infer/models/mt3_pytorch/contrib/spectrograms_torch.py
mt3_infer/models/mt3_pytorch/contrib/vocabularies.py
mt3_infer/models/yourmt3/__init__.py
mt3_infer/models/yourmt3/inference_loader.py
mt3_infer/models/yourmt3/model_helper.py
mt3_infer/models/yourmt3/config/__init__.py
mt3_infer/models/yourmt3/config/config.py
mt3_infer/models/yourmt3/config/data_presets.py
mt3_infer/models/yourmt3/config/task.py
mt3_infer/models/yourmt3/config/vocabulary.py
mt3_infer/models/yourmt3/model/__init__.py
mt3_infer/models/yourmt3/model/conformer_helper.py
mt3_infer/models/yourmt3/model/conformer_mod.py
mt3_infer/models/yourmt3/model/conv_block.py
mt3_infer/models/yourmt3/model/ff_layer.py
mt3_infer/models/yourmt3/model/init_train.py
mt3_infer/models/yourmt3/model/lm_head.py
mt3_infer/models/yourmt3/model/lr_scheduler.py
mt3_infer/models/yourmt3/model/ops.py
mt3_infer/models/yourmt3/model/optimizers.py
mt3_infer/models/yourmt3/model/perceiver_helper.py
mt3_infer/models/yourmt3/model/perceiver_mod.py
mt3_infer/models/yourmt3/model/pitchshift_layer.py
mt3_infer/models/yourmt3/model/positional_encoding.py
mt3_infer-0.1.1.dist-info/METADATA
mt3_infer-0.1.1.dist-info/WHEEL
mt3_infer-0.1.1.dist-info/entry_points.txt
mt3_infer-0.1.1.dist-info/licenses/LICENSE
mt3_infer-0.1.1.dist-info/RECORD
