Metadata-Version: 2.4
Name: mt3-infer
Version: 0.1.1
Summary: Unified, inference-only toolkit for MT3 model family (Magenta MT3, MR-MT3, MT3-PyTorch, YourMT3)
Project-URL: Homepage, https://github.com/openmirlab/mt3-infer
Project-URL: Documentation, https://github.com/openmirlab/mt3-infer/blob/master/README.md
Project-URL: Repository, https://github.com/openmirlab/mt3-infer
Project-URL: Issues, https://github.com/openmirlab/mt3-infer/issues
Author: MT3-Infer Contributors
License: MIT License
License-File: LICENSE
Keywords: audio,midi,mir,mt3,music,transcription
Classifier: Development Status :: 3 - Alpha
Classifier: Intended Audience :: Developers
Classifier: Intended Audience :: Science/Research
Classifier: License :: OSI Approved :: MIT License
Classifier: Programming Language :: Python :: 3
Classifier: Programming Language :: Python :: 3.8
Classifier: Programming Language :: Python :: 3.9
Classifier: Programming Language :: Python :: 3.10
Classifier: Programming Language :: Python :: 3.11
Classifier: Programming Language :: Python :: 3.12
Classifier: Topic :: Multimedia :: Sound/Audio :: Analysis
Classifier: Topic :: Scientific/Engineering :: Artificial Intelligence
Requires-Python: >=3.8
Requires-Dist: einops>=0.4.1
Requires-Dist: librosa>=0.9.1
Requires-Dist: lightning>=2.3.0
Requires-Dist: matplotlib>=3.8.0
Requires-Dist: mido>=1.3.0
Requires-Dist: mir-eval>=0.8.2
Requires-Dist: note-seq==0.0.3
Requires-Dist: numpy>=1.22
Requires-Dist: pretty-midi>=0.2.10
Requires-Dist: protobuf<4.0,>=3.20.3
Requires-Dist: pyloudnorm>=0.1.1
Requires-Dist: pyrubberband>=0.4.0
Requires-Dist: pyyaml>=6.0.2
Requires-Dist: scipy<1.15.0,>=1.10.0
Requires-Dist: soundfile>=0.13.1
Requires-Dist: soxr>=1.0.0
Requires-Dist: torch==2.7.1
Requires-Dist: torchaudio==2.7.1
Requires-Dist: torchvision==0.22.1
Requires-Dist: tqdm>=4.67.1
Requires-Dist: transformers~=4.30.2
Provides-Extra: all
Requires-Dist: tensorflow>=2.13.0; extra == 'all'
Requires-Dist: torch==2.7.1; extra == 'all'
Requires-Dist: torchaudio==2.7.1; extra == 'all'
Requires-Dist: torchvision==0.22.1; extra == 'all'
Provides-Extra: dev
Requires-Dist: black>=23.0.0; extra == 'dev'
Requires-Dist: mypy>=1.0.0; extra == 'dev'
Requires-Dist: pytest-cov>=4.0.0; extra == 'dev'
Requires-Dist: pytest>=7.0.0; extra == 'dev'
Requires-Dist: ruff>=0.1.0; extra == 'dev'
Requires-Dist: scipy>=1.10.0; extra == 'dev'
Provides-Extra: synthesis
Requires-Dist: midi2audio>=0.1.1; extra == 'synthesis'
Provides-Extra: tensorflow
Requires-Dist: tensorflow>=2.13.0; extra == 'tensorflow'
Provides-Extra: torch
Requires-Dist: torch==2.7.1; extra == 'torch'
Requires-Dist: torchaudio==2.7.1; extra == 'torch'
Requires-Dist: torchvision==0.22.1; extra == 'torch'
